spotifyconverter
tests
