Metadata-Version: 1.0
Name: spotifyPlaylistConverter
Version: 1.4
Summary: scripts to convert a Spotify playlist to a Google Music one
Home-page: https://github.com/Bachmann1234/playlistConverter
Author: Matt Bachmann
Author-email: UNKNOWN
License: Apache 2.0
Platform: UNKNOWN
